juptest/__init__.py
juptest/module.py
juptest-0.1.0.dist-info/METADATA
juptest-0.1.0.dist-info/WHEEL
juptest-0.1.0.dist-info/top_level.txt
juptest-0.1.0.dist-info/RECORD
